pdb_attach/VERSION.txt
pdb_attach/__init__.py
pdb_attach/__init__.pyi
pdb_attach/__main__.py
pdb_attach/detach.py
pdb_attach/detach.pyi
pdb_attach/pdb_signal.py
pdb_attach/pdb_signal.pyi
pdb_attach/pdb_socket.py
pdb_attach/pdb_socket.pyi
pdb_attach/py.typed
pdb_attach-3.0.1.dist-info/LICENSE
pdb_attach-3.0.1.dist-info/METADATA
pdb_attach-3.0.1.dist-info/WHEEL
pdb_attach-3.0.1.dist-info/top_level.txt
pdb_attach-3.0.1.dist-info/RECORD
