Metadata-Version: 2.1
Name: pdb-attach
Version: 3.0.1
Summary: A python debugger that can attach to running processes.
Home-page: https://github.com/smitchell556/pdb-attach
Author: Spencer Mitchell
Author-email: smitchell556@gmail.com
License: BSD 3-Clause
Project-URL: Documentation, https://github.com/smitchell556/pdb-attach
Project-URL: Source, https://github.com/smitchell556/pdb-attach
Project-URL: Bug Tracker, https://github.com/smitchell556/pdb-attach/issues
Keywords: pdb debug debugger process
Platform: UNKNOWN
Classifier: Intended Audience :: Developers
Classifier: License :: OSI Approved :: BSD License
Classifier: Topic :: Software Development :: Libraries :: Python Modules
Classifier: Operating System :: POSIX
Classifier: Programming Language :: Python :: 2.7
Classifier: Programming Language :: Python :: 3.3
Classifier: Programming Language :: Python :: 3.4
Classifier: Programming Language :: Python :: 3.5
Classifier: Programming Language :: Python :: 3.6
Classifier: Programming Language :: Python :: 3.7
Classifier: Programming Language :: Python :: 3.8
Classifier: Programming Language :: Python :: 3.9
Requires-Python: >=2.7, !=3.0.*, !=3.1.*, !=3.2.*, <4
